pinform/__init__.py
pinform/client.py
pinform/utils.py
pinform/fields/__init__.py
pinform/tags/__init__.py
pinform-0.9.1.dist-info/LICENSE
pinform-0.9.1.dist-info/METADATA
pinform-0.9.1.dist-info/WHEEL
pinform-0.9.1.dist-info/top_level.txt
pinform-0.9.1.dist-info/RECORD
