Metadata-Version: 2.1
Name: pinform
Version: 0.9.1
Summary: Python InfluxDB ORM (OSTM)
Home-page: https://github.com/sinarezaei/pinform
Author: Sina Rezaei
Author-email: sinarezaei1991@gmail.com
License: MIT
Platform: UNKNOWN
Classifier: Programming Language :: Python :: 3
Classifier: License :: OSI Approved :: MIT License
Classifier: Operating System :: OS Independent
